lucifer/Iterable.py
lucifer/ProgressBar.py
lucifer/__init__.py
lucifer/colour.py
lucifer/map.py
lucifer-1.3.dist-info/LICENSE
lucifer-1.3.dist-info/METADATA
lucifer-1.3.dist-info/WHEEL
lucifer-1.3.dist-info/top_level.txt
lucifer-1.3.dist-info/RECORD
