Metadata-Version: 2.1
Name: lucifer
Version: 1.3
Summary: Python library for creating progress bars
Home-page: https://github.com/idin/lucifer
Author: Idin
Author-email: py@idin.ca
License: MIT
Platform: UNKNOWN
Requires-Python: ~=3.6
